LICENSE
MANIFEST.in
README.rst
setup.py
stata_setup.py
stata_setup.egg-info/PKG-INFO
stata_setup.egg-info/SOURCES.txt
stata_setup.egg-info/dependency_links.txt
stata_setup.egg-info/requires.txt
stata_setup.egg-info/top_level.txt