Metadata-Version: 2.1
Name: stata-setup
Version: 0.1.3
Summary: A module for configuring and initializing Stata within Python
Home-page: https://www.stata.com/python/pystata
Author: StataCorp LLC
Author-email: tech-support@stata.com
License: Apache Software License 2.0
Download-URL: http://pypi.python.org/pypi/stata_setup
Platform: UNKNOWN
Classifier: License :: OSI Approved :: Apache Software License
Classifier: Operating System :: OS Independent
License-File: LICENSE
